numeronym
