Metadata-Version: 1.0
Name: numeronym
Version: 1.0.1
Summary: A simple library for generating numeronyms
Home-page: https://github.com/bmelton/numeronym/
Author: Barry Melton
Author-email: barry.melton@gmail.com.com
License: BSD
Platform: UNKNOWN
Classifier: License :: OSI Approved :: BSD License
Classifier: Programming Language :: Python
Classifier: Programming Language :: Python :: 2.5
Classifier: Programming Language :: Python :: 2.6
Classifier: Programming Language :: Python :: 2.7
Classifier: Programming Language :: Python :: 3.2
Classifier: Programming Language :: Python :: 3.3
Classifier: Topic :: Software Development :: Libraries :: Python Modules
